arq_base_python/__init__.py
arq_base_python-1.0.9.dist-info/METADATA
arq_base_python-1.0.9.dist-info/WHEEL
arq_base_python-1.0.9.dist-info/top_level.txt
arq_base_python-1.0.9.dist-info/RECORD
