Metadata-Version: 2.4
Name: arq_base_python
Version: 1.0.9
Summary: Una libreria simple de python
Requires-Python: >=3.8
